{
  "current_product_downloads": 1688,
  "cumulative_product_downloads": 1688,
  "current_asset_downloads": 2216,
  "cumulative_asset_downloads": 3006,
  "cumulative_downloads": 3006,
  "current_checksum_downloads": 528,
  "visible_product_downloads": 730,
  "visible_asset_downloads": 926,
  "visible_checksum_downloads": 196,
  "archived_product_downloads": 958,
  "archived_asset_downloads": 1290,
  "archived_checksum_downloads": 332,
  "last_seen_product_total": 1688,
  "last_seen_asset_total": 2216,
  "last_seen_current_total": 2216,
  "current_total_downloads": 2216,
  "release_count": 25,
  "visible_release_count": 8,
  "archived_release_count": 17,
  "asset_count": 53,
  "visible_asset_count": 17,
  "archived_asset_count": 36,
  "product_asset_count": 28,
  "visible_product_asset_count": 9,
  "archived_product_asset_count": 19,
  "checksum_asset_count": 25,
  "visible_checksum_asset_count": 8,
  "archived_checksum_asset_count": 17,
  "updated_at": "2026-05-31T13:06:08.5268134Z",
  "source": "github-releases-assets-plus-archive",
  "notes": "Product downloads count visible release assets ending in .exe, .zip, or .msi plus archived downloads from deleted releases. Checksum assets are excluded from product downloads."
}
